{"property_id": "1634225963", "price": "\u20b9 24,000", "image_url": "https://apollo-singapore.akamaized.net:443/v1/files/4ivjvxshtx0q3-IN/image;s=120x160", "description": "Looking for a rental property in Calicut?  Looking for a rental House in city ?? Welcome to Brokees        We are Kerala leading real estate marketing company specialising in the end-to-end solution for property renting,  leasing,  buying and selling. Which present in Calicut Cochin Kannur ,Trivandram, Thrissur and Kottayam. we are your most reliable and trusted real estate partner.                      Your search for a rental flat, Villa or house ends here. We are an expert property finder with serving more than hundred thousand tenants across Kerala.      \u2022) 6 month rental replacement guarantee,  \u2022) Deep cleaned and sanitized units,  \u2022)  Basic connection setup assistance and \u2022) Hassle-free documentation  \u2022) 30% off in Commission charges      These makes us way ahead then our competitors. Just give us 24 working hours to show you the exact property you have been hunting for. \u0d0e\u0d28\u0d4d\u0d24\u0d3f\u0d28\u0d3e \u0d1a\u0d19\u0d4d\u0d19\u0d3e\u0d24\u0d3f \u0d2b\u0d4d\u0d32\u0d3e\u0d31\u0d4d\u0d31\u0d41\u0d02 /\u0d35\u0d40\u0d1f\u0d41\u0d02 \u0d24\u0d2a\u0d4d\u0d2a\u0d3f \u0d35\u0d3f\u0d32\u0d2a\u0d4d\u0d2a\u0d46\u0d1f\u0d4d\u0d1f \u0d38\u0d2e\u0d2f\u0d02 \u0d15\u0d33\u0d2f\u0d41\u0d28\u0d4d\u0d28\u0d46 ?  brokees \u0d7d \u0d35\u0d28\u0d4d\u0d28\u0d3e\u0d7d \u0d0e\u0d32\u0d4d\u0d32\u0d3e\u0d24\u0d4d\u0d24\u0d3f\u0d28\u0d41\u0d02 \u0d09\u0d24\u0d4d\u0d24\u0d30\u0d02 \u0d06\u0d2f\u0d3f\u0d32\u0d4d\u0d32\u0d47 . \u0d28\u0d3f\u0d19\u0d4d\u0d19\u0d33\u0d41\u0d1f\u0d46 \u0d2e\u0d28\u0d38\u0d3f\u0d32\u0d46 \u0d06\u0d35\u0d3f\u0d36\u0d4d\u0d2f\u0d19\u0d4d\u0d19\u0d7e \u0d05\u0d31\u0d3f\u0d2f\u0d3f\u0d15\u0d4d\u0d15\u0d41 ,\u0d1a\u0d47\u0d30\u0d41\u0d28\u0d4d\u0d28 \u0d2b\u0d4d\u0d32\u0d3e\u0d31\u0d4d\u0d31\u0d41\u0d15\u0d7e /\u0d35\u0d40\u0d1f\u0d41\u0d15\u0d7e \u0d1e\u0d19\u0d4d\u0d19\u0d7e \u0d28\u0d7d\u0d15\u0d3e\u0d02  HURRY GET YOUR APPOINTMENT NOW", "location": "Thondayad,Kozhikode,Kerala", "property type": "Apartments", "bathrooms": " 3 Ba ", "bedrooms": "3 Bds ", "furnishing": "Semi-Furnished", "super buildup area": "1950", "carpet area": "1690", "total_sqft": " 1950 ft2"}
{"property_id": "1634220798", "price": "\u20b9 25,000", "image_url": "https://apollo-singapore.akamaized.net:443/v1/files/q2qfe0st8ok82-IN/image;s=120x90", "description": "\u0d38\u0d02\u0d17\u0d24\u0d3f \u0d15\u0d4a\u0d31\u0d4b\u0d23 \u0d12\u0d15\u0d4d\u0d15\u0d46 \u0d05\u0d32\u0d4d\u0d32\u0d47 \u0d1a\u0d47\u0d1f\u0d4d\u0d1f\u0d3e , \u0d05\u0d24\u0d41\u0d15\u0d4a\u0d23\u0d4d\u0d1f\u0d4d \u0d35\u0d3e\u0d1f\u0d15 \u0d12\u0d15\u0d4d\u0d15\u0d46 \u0d12\u0d28\u0d4d\u0d28\u0d4d \u0d12\u0d24\u0d41\u0d19\u0d4d\u0d19\u0d3f \u0d15\u0d3f\u0d1f\u0d4d\u0d1f\u0d23 \u0d2b\u0d4d\u0d32\u0d3e\u0d31\u0d4d\u0d31\u0d41\u0d15\u0d7e \u0d28\u0d4b\u0d15\u0d4d\u0d15\u0d3e\u0d02 .  Welcome to Brokees. We are Keralas leading Real eatate marketing company focusing on the end to end solution  Get 30% off in Commission charges", "location": "Thondayad,Kozhikode,Kerala", "property type": "Apartments", "bathrooms": " 2 Ba ", "bedrooms": "2 Bds ", "furnishing": "Furnished", "super buildup area": "1345", "carpet area": "1010", "total_sqft": " 1345 ft2"}
{"property_id": "1634214609", "price": "\u20b9 20,000", "image_url": "https://apollo-singapore.akamaized.net:443/v1/files/1whwb56vqym83-IN/image;s=120x90", "description": "Looking for a rental House in city ?  \u0d15\u0d4a\u0d31\u0d4b\u0d23 \u0d12\u0d15\u0d4d\u0d15\u0d46 \u0d06\u0d23\u0d4d \u0d1a\u0d47\u0d1f\u0d4d\u0d1f\u0d3e , \u0d35\u0d40\u0d1f\u0d4d \u0d24\u0d2a\u0d4d\u0d2a\u0d3f \u0d05\u0d32\u0d1e\u0d4d\u0d1e\u0d41 \u0d15\u0d4a\u0d31\u0d4b\u0d23 \u0d35\u0d30\u0d41\u0d24\u0d4d\u0d24\u0d23\u0d4b ?  \u0d05\u0d24\u0d41\u0d15\u0d4a\u0d23\u0d4d\u0d1f\u0d4d \u0d35\u0d47\u0d17\u0d02 \u0d35\u0d3f\u0d33\u0d3f\u0d1a\u0d4d\u0d1a\u0d4b\u0d33\u0d40 . \u0d28\u0d3f\u0d19\u0d4d\u0d19\u0d33\u0d41\u0d1f\u0d46 \u0d06\u0d35\u0d3f\u0d36\u0d4d\u0d2f\u0d02 \u0d2a\u0d31\u0d1e\u0d4d\u0d1e\u0d4b\u0d33\u0d42 , \u0d07\u0d37\u0d4d\u0d1f\u0d4b\u0d33\u0d4d\u0d33 \u0d35\u0d40\u0d1f\u0d4d \u0d2a\u0d3f\u0d1f\u0d3f\u0d1a\u0d4d\u0d1a\u0d4b\u0d33\u0d40", "location": "Thondayad,Kozhikode,Kerala", "property type": "Houses & Villas", "bathrooms": " 3 Ba ", "bedrooms": "4 Bds ", "furnishing": "Semi-Furnished", "super buildup area": "2300", "carpet area": "2100", "total_sqft": " 2300 ft2"}
{"property_id": "1629313959", "price": "\u20b9 27,000", "image_url": "https://apollo-singapore.akamaized.net:443/v1/files/8ybpw63bd5nb3-IN/image;s=120x67", "description": "Looking for a rental property in Calicut?  Looking for a rental House in city ?? Welcome to Brokees        We are Kerala leading real estate marketing company specialising in the end-to-end solution for property renting,  leasing,  buying and selling. Which present in Calicut Cochin Kannur ,Trivandram, Thrissur and Kottayam. we are your most reliable and trusted real estate partner.                      Your search for a rental flat, Villa or house ends here. We are an expert property finder with serving more than hundred thousand tenants across Kerala.      \u2022) 6 month rental replacement guarantee,  \u2022) Deep cleaned and sanitized units,  \u2022)  Basic connection setup assistance and \u2022) Hassle-free documentation  \u2022) 30% off in Commission charges      These makes us way ahead then our competitors. Just give us 24 working hours to show you the exact property you have been hunting for. \u0d0e\u0d28\u0d4d\u0d24\u0d3f\u0d28\u0d3e \u0d1a\u0d19\u0d4d\u0d19\u0d3e\u0d24\u0d3f \u0d2b\u0d4d\u0d32\u0d3e\u0d31\u0d4d\u0d31\u0d41\u0d02 /\u0d35\u0d40\u0d1f\u0d41\u0d02 \u0d24\u0d2a\u0d4d\u0d2a\u0d3f \u0d35\u0d3f\u0d32\u0d2a\u0d4d\u0d2a\u0d46\u0d1f\u0d4d\u0d1f \u0d38\u0d2e\u0d2f\u0d02 \u0d15\u0d33\u0d2f\u0d41\u0d28\u0d4d\u0d28\u0d46 ?  brokees \u0d7d \u0d35\u0d28\u0d4d\u0d28\u0d3e\u0d7d \u0d0e\u0d32\u0d4d\u0d32\u0d3e\u0d24\u0d4d\u0d24\u0d3f\u0d28\u0d41\u0d02 \u0d09\u0d24\u0d4d\u0d24\u0d30\u0d02 \u0d06\u0d2f\u0d3f\u0d32\u0d4d\u0d32\u0d47 . \u0d28\u0d3f\u0d19\u0d4d\u0d19\u0d33\u0d41\u0d1f\u0d46 \u0d2e\u0d28\u0d38\u0d3f\u0d32\u0d46 \u0d06\u0d35\u0d3f\u0d36\u0d4d\u0d2f\u0d19\u0d4d\u0d19\u0d7e \u0d05\u0d31\u0d3f\u0d2f\u0d3f\u0d15\u0d4d\u0d15\u0d41 ,\u0d1a\u0d47\u0d30\u0d41\u0d28\u0d4d\u0d28 \u0d2b\u0d4d\u0d32\u0d3e\u0d31\u0d4d\u0d31\u0d41\u0d15\u0d7e /\u0d35\u0d40\u0d1f\u0d41\u0d15\u0d7e \u0d1e\u0d19\u0d4d\u0d19\u0d7e \u0d28\u0d7d\u0d15\u0d3e\u0d02  HURRY GET YOUR APPOINTMENT NOW", "location": "Thondayad,Kozhikode,Kerala", "property type": "Houses & Villas", "bathrooms": " 3 Ba ", "bedrooms": "4 Bds ", "furnishing": "Semi-Furnished", "super buildup area": "2215", "carpet area": "2015", "total_sqft": " 2215 ft2"}
{"property_id": "1626404582", "price": "\u20b9 21,000", "image_url": "https://apollo-singapore.akamaized.net:443/v1/files/702f78staseh1-IN/image;s=120x90", "description": "Looking for a Rental House in kozhikode?  Welcome to Brokees                  We are Kerala leading real estate marketing company specialising in the end-to-end solution for property renting,  leasing,  buying and selling. Which present in Calicut Cochin Kannur Thrissur and Kottayam. we are your most reliable and trusted real estate partner.                      Your search for a rental flat, Villa or house ends here. We are an expert property finder with serving more than hundred thousand buyers across Kerala.            These makes us way ahead then our competitors. Just give us 24 working hours to show you the exact property you have been hunting for.  Get 30% off on Commission charges   HURRY GET YOUR APPOINTMENT NOW", "location": "Thondayad,Kozhikode,Kerala", "property type": "Houses & Villas", "bathrooms": " 3 Ba ", "bedrooms": "3 Bds ", "furnishing": "Semi-Furnished", "super buildup area": "2100", "carpet area": "1960", "total_sqft": " 2100 ft2"}
{"property_id": "1609793534", "price": "\u20b9 28,000", "image_url": "https://apollo-singapore.akamaized.net:443/v1/files/arw3wuubqet21-IN/image;s=120x90", "description": "Welcome to Brokees         We are Kerala leading real estate marketing company specialising in the end-to-end solution for property renting,  leasing,  buying and selling. Which present in Calicut Cochin Kannur Thrissur and Kottayam. we are your most reliable and trusted real estate partner.                      Your search for a rental flat, Villa or house ends here. We are an expert property finder with serving more than hundred thousand tenants across Kerala.      \u2022) 6 month rental replacement guarantee,  \u2022) Deep cleaned and sanitized units,  \u2022)  Basic connection setup assistance and \u2022) Hassle-free documentation       These makes us way ahead then our competitors. Just give us 24 working hours to show you the exact property you have been hunting for.   HURRY GET YOUR APPOINTMENT NOW", "location": "Thondayad,Kozhikode,Kerala", "property type": "Houses & Villas", "bathrooms": " 4 Ba ", "bedrooms": "4 Bds ", "furnishing": "Furnished", "super buildup area": "2680", "carpet area": "2380", "total_sqft": " 2680 ft2"}
{"property_id": "1634690837", "price": "\u20b9 22,000", "image_url": "https://apollo-singapore.akamaized.net:443/v1/files/dqf3td5in4fq1-IN/image;s=120x159", "description": "\u0d2a\u0d41\u0d24\u0d41\u0d2a\u0d41\u0d24\u0d4d\u0d24\u0d7b \u0d35\u0d40\u0d1f\u0d41\u0d15\u0d7e \u0d12\u0d30\u0d41\u0d2a\u0d3e\u0d1f\u0d4d \u0d06\u0d33\u0d3f\u0d32\u0d4d\u0d32\u0d3e\u0d24\u0d46 \u0d05\u0d1f\u0d1e\u0d4d\u0d1e\u0d41 \u0d15\u0d3f\u0d1f\u0d15\u0d4d\u0d15\u0d41\u0d28\u0d4d\u0d28\u0d41 . \u0d2a\u0d32\u0d7c\u0d15\u0d4d\u0d15\u0d41\u0d02 \u0d05\u0d24\u0d4d \u0d35\u0d3e\u0d1f\u0d15\u0d2f\u0d4d\u0d15\u0d4d\u0d15\u0d4d \u0d15\u0d4a\u0d1f\u0d41\u0d15\u0d4d\u0d15\u0d41\u0d35\u0d3e\u0d28\u0d41\u0d33\u0d4d\u0d33 \u0d2e\u0d1f\u0d3f ,,\u0d05\u0d24\u0d4d \u0d28\u0d36\u0d3f\u0d2a\u0d4d\u0d2a\u0d3f\u0d15\u0d4d\u0d15\u0d41\u0d2e\u0d4b \u0d0e\u0d28\u0d4d\u0d28 \u0d2d\u0d2f\u0d02 \u0d15\u0d4a\u0d23\u0d4d\u0d1f\u0d4d \u0d2e\u0d3e\u0d24\u0d4d\u0d30\u0d2e\u0d3e\u0d23\u0d4d . \u0d0e\u0d28\u0d4d\u0d28\u0d3e\u0d7d \u0d38\u0d4d\u0d35\u0d28\u0d4d\u0d24\u0d02 \u0d35\u0d40\u0d1f\u0d4d\u200c \u0d2a\u0d4b\u0d32\u0d46 \u0d28\u0d3f\u0d19\u0d4d\u0d19\u0d7e \u0d05\u0d24\u0d4d \u0d28\u0d4b\u0d15\u0d4d\u0d15\u0d41\u0d2e\u0d46\u0d19\u0d4d\u0d15\u0d3f\u0d7d \u0d05\u0d24\u0d4d\u0d24\u0d30\u0d02 \u0d35\u0d40\u0d1f\u0d41\u0d15\u0d7e \u0d1e\u0d19\u0d4d\u0d19\u0d7e \u0d28\u0d7d\u0d15\u0d3e\u0d02 \u0d28\u0d3f\u0d19\u0d4d\u0d19\u0d7e\u0d15\u0d4d\u0d15\u0d4d .   \u0d15\u0d4a\u0d31\u0d4b\u0d23 \u0d06\u0d23\u0d4d \u0d1a\u0d47\u0d1f\u0d4d\u0d1f\u0d3e . \u0d06\u0d2f\u0d24\u0d3f\u0d28\u0d3e\u0d7d \u0d35\u0d40\u0d1f\u0d4d\u200c \u0d24\u0d2a\u0d4d\u0d2a\u0d3f \u0d05\u0d32\u0d2f\u0d41\u0d28\u0d4d\u0d28\u0d24\u0d4d \u0d35\u0d32\u0d3f\u0d2f \u0d05\u0d2a\u0d15\u0d1f\u0d02 \u0d35\u0d3f\u0d33\u0d3f\u0d1a\u0d4d\u0d1a\u0d41 \u0d35\u0d30\u0d41\u0d24\u0d4d\u0d24\u0d41\u0d02  \u0d28\u0d3f\u0d19\u0d4d\u0d19\u0d33\u0d41\u0d1f\u0d46 \u0d35\u0d3f\u0d30\u0d7d \u0d24\u0d41\u0d2e\u0d4d\u0d2a\u0d3f\u0d7d \u0d07\u0d2a\u0d4d\u0d2a\u0d4b\u0d7e \u0d0e\u0d32\u0d4d\u0d32\u0d3e \u0d13\u0d2a\u0d4d\u0d37\u0d28\u0d41\u0d02 \u0d0e\u0d24\u0d4d\u0d24\u0d41\u0d02 Brokees \u0d32\u0d42\u0d1f\u0d46   Get your appointment now", "location": "Thondayad,Kozhikode,Kerala", "property type": "Houses & Villas", "bathrooms": " 3 Ba ", "bedrooms": "3 Bds ", "furnishing": "Semi-Furnished", "super buildup area": "2090", "carpet area": "1980", "total_sqft": " 2090 ft2"}
{"property_id": "1634684414", "price": "\u20b9 20,000", "image_url": "https://apollo-singapore.akamaized.net:443/v1/files/2ayshpm0cx0o-IN/image;s=120x118", "description": "\u0d15\u0d41\u0d1e\u0d4d\u0d1e\u0d41 \u0d15\u0d41\u0d1f\u0d41\u0d02\u0d2c\u0d2e\u0d46\u0d19\u0d4d\u0d15\u0d3f\u0d7d \u0d28\u0d3f\u0d19\u0d4d\u0d19\u0d7e\u0d15\u0d4d\u0d15\u0d4d \u0d1a\u0d47\u0d30\u0d41\u0d28\u0d4d\u0d28 \u0d12\u0d30\u0d41 \u0d15\u0d41\u0d1e\u0d4d\u0d1e\u0d41 \u0d35\u0d40\u0d1f\u0d4d \u0d07\u0d24\u0d3e .  \u0d07\u0d24\u0d41\u0d2a\u0d4b\u0d32\u0d41\u0d33\u0d4d\u0d33 \u0d15\u0d41\u0d1e\u0d4d\u0d1e\u0d41 \u0d35\u0d40\u0d1f\u0d41\u0d15\u0d7e \u0d28\u0d4b\u0d15\u0d4d\u0d15\u0d3e\u0d02 brokees \u0d32\u0d42\u0d1f\u0d46 .  Get your appointment now", "location": "Thondayad,Kozhikode,Kerala", "property type": "Houses & Villas", "bathrooms": " 2 Ba ", "bedrooms": "3 Bds ", "furnishing": "Semi-Furnished", "super buildup area": "1500", "carpet area": "1400", "total_sqft": " 1500 ft2"}
{"property_id": "1634602966", "price": "\u20b9 20,000", "image_url": "https://apollo-singapore.akamaized.net:443/v1/files/713ffhl9umzt2-IN/image;s=120x160", "description": "\u0d05\u0d27\u0d3f\u0d15\u0d02 \u0d35\u0d46\u0d1a\u0d4d\u0d1a\u0d4d \u0d15\u0d46\u0d1f\u0d4d\u0d1f\u0d32\u0d4a\u0d28\u0d4d\u0d28\u0d41\u0d02 \u0d07\u0d32\u0d4d\u0d32\u0d3e\u0d24\u0d4d\u0d24 \u0d38\u0d3f\u0d2e\u0d4d\u0d2a\u0d3f\u0d7e \u0d06\u0d2f \u0d12\u0d30\u0d41 \u0d2b\u0d4d\u0d32\u0d3e\u0d31\u0d4d\u0d31\u0d4d \u0d35\u0d3e\u0d1f\u0d15\u0d2f\u0d4d\u0d15\u0d4d\u0d15\u0d4d \u0d0e\u0d1f\u0d41\u0d15\u0d4d\u0d15\u0d3e\u0d02 .  \u0d35\u0d30\u0d42 Brokees \u0d7d", "location": "Thondayad,Kozhikode,Kerala", "property type": "Apartments", "bathrooms": " 2 Ba ", "bedrooms": "2 Bds ", "furnishing": "Furnished", "super buildup area": "1870", "carpet area": "1590", "total_sqft": " 1870 ft2"}
{"property_id": "1634602278", "price": "\u20b9 24,500", "image_url": "https://apollo-singapore.akamaized.net:443/v1/files/okye7v0k1s3o2-IN/image;s=120x90", "description": "\u0d15\u0d4a\u0d31\u0d4b\u0d23 \u0d06\u0d2f\u0d24\u0d41 \u0d15\u0d4a\u0d23\u0d4d\u0d1f\u0d4d \u0d2a\u0d32 \u0d07\u0d1f\u0d19\u0d4d\u0d19\u0d33\u0d41\u0d02 \u0d05\u0d1f\u0d1a\u0d4d\u0d1a\u0d3f\u0d30\u0d3f\u0d15\u0d4d\u0d15\u0d41\u0d28\u0d4d\u0d28\u0d41 . \u0d06\u0d2f\u0d24\u0d41 \u0d15\u0d4a\u0d23\u0d4d\u0d1f\u0d4d \u0d28\u0d3f\u0d19\u0d4d\u0d19\u0d33\u0d4d\u0d15\u0d4d\u0d15\u0d4d \u0d35\u0d47\u0d23\u0d4d\u0d1f \u0d13\u0d2a\u0d4d\u0d37\u0d7b \u0d1e\u0d19\u0d4d\u0d19\u0d7e \u0d28\u0d7d\u0d15\u0d3e\u0d02 . \u0d38\u0d2e\u0d2f\u0d02 \u0d32\u0d3e\u0d2d\u0d3f\u0d15\u0d4d\u0d15\u0d3e\u0d02 , \u0d15\u0d4a\u0d31\u0d4b\u0d23 \u0d35\u0d30\u0d3e\u0d24\u0d46\u0d2f\u0d41\u0d02 \u0d28\u0d4b\u0d15\u0d4d\u0d15\u0d3e\u0d02 .   \u0d15\u0d4b\u0d34\u0d3f\u0d15\u0d4d\u0d15\u0d4b\u0d1f\u0d4d \u0d28\u0d32\u0d4d\u0d32 \u0d28\u0d32\u0d4d\u0d32 \u0d2b\u0d4d\u0d32\u0d3e\u0d31\u0d4d\u0d31\u0d41\u0d15\u0d7e \u0d39\u0d4d\u0d28\u0d19\u0d4d\u0d19\u0d7e \u0d28\u0d7d\u0d15\u0d3e\u0d02", "location": "Thondayad,Kozhikode,Kerala", "property type": "Apartments", "bathrooms": " 2 Ba ", "bedrooms": "2 Bds ", "furnishing": "Furnished", "super buildup area": "1860", "carpet area": "1630", "total_sqft": " 1860 ft2"}
{"property_id": "1634601568", "price": "\u20b9 23,500", "image_url": "https://apollo-singapore.akamaized.net:443/v1/files/ahmmkckx9by01-IN/image;s=120x90", "description": "\u0d2b\u0d4d\u0d32\u0d3e\u0d31\u0d4d\u0d31\u0d4d \u0d0e\u0d1f\u0d41\u0d15\u0d4d\u0d15\u0d41\u0d2e\u0d4d\u0d2a\u0d4b\u0d7e \u0d28\u0d32\u0d4d\u0d32\u0d24\u0d3e\u0d23\u0d46\u0d19\u0d4d\u0d15\u0d3f\u0d32\u0d32\u0d4d\u0d32\u0d47 \u0d1a\u0d47\u0d1f\u0d4d\u0d1f\u0d3e \u0d06 \u0d12\u0d30\u0d41 \u0d35\u0d48\u0d2c\u0d4d \u0d09\u0d23\u0d4d\u0d1f\u0d3e\u0d35\u0d41\u0d33\u0d4d\u0d33\u0d41 . \u0d2a\u0d4d\u0d30\u0d24\u0d4d\u0d2f\u0d47\u0d15\u0d3f\u0d1a\u0d4d\u0d1a\u0d4d \u0d08 \u0d15\u0d4a\u0d31\u0d4b\u0d23 \u0d1f\u0d48\u0d2e\u0d3f\u0d7d \u0d35\u0d46\u0d33\u0d4d\u0d33\u0d35\u0d41\u0d02 \u0d15\u0d42\u0d1f\u0d41\u0d24\u0d7d \u0d2b\u0d4d\u0d32\u0d3e\u0d31\u0d4d\u0d31\u0d3f\u0d32\u0d41\u0d02 \u0d35\u0d40\u0d1f\u0d4d\u0d1f\u0d3f\u0d32\u0d41\u0d02 \u0d06\u0d2f\u0d3f \u0d1a\u0d46\u0d32\u0d35\u0d34\u0d3f\u0d15\u0d4d\u0d15\u0d41\u0d28\u0d4d\u0d28 \u0d1f\u0d48\u0d2e\u0d3f\u0d7d \u0d28\u0d3f\u0d19\u0d4d\u0d19\u0d33\u0d46\u0d1f\u0d41\u0d15\u0d4d\u0d15\u0d41\u0d28\u0d4d\u0d28\u0d24\u0d4d \u0d06 \u0d12\u0d30\u0d41 \u0d35\u0d48\u0d2c\u0d4d \u0d09\u0d33\u0d4d\u0d33 \u0d2b\u0d4d\u0d32\u0d3e\u0d31\u0d4d\u0d31\u0d4d \u0d06\u0d23\u0d46\u0d19\u0d4d\u0d15\u0d3f\u0d32\u0d32\u0d4d\u0d32\u0d47 \u0d1a\u0d47\u0d1f\u0d4d\u0d1f\u0d3e \u0d12\u0d30\u0d41 \u0d38\u0d41\u0d17\u0d2e\u0d41\u0d33\u0d4d\u0d33\u0d41 .  \u0d06\u0d2f\u0d24\u0d3f\u0d28\u0d3e\u0d7d \u0d28\u0d4b\u0d15\u0d4d\u0d15\u0d3e\u0d02 \u0d28\u0d32\u0d4d\u0d32 \u0d2b\u0d4d\u0d32\u0d3e\u0d31\u0d4d\u0d31\u0d41\u0d15\u0d7e  Brokees \u0d32\u0d42\u0d1f\u0d46", "location": "Thondayad,Kozhikode,Kerala", "property type": "Apartments", "bathrooms": " 2 Ba ", "bedrooms": "2 Bds ", "furnishing": "Furnished", "super buildup area": "1350", "carpet area": "1084", "total_sqft": " 1350 ft2"}
{"property_id": "1634599410", "price": "\u20b9 18,000", "image_url": "https://apollo-singapore.akamaized.net:443/v1/files/lnb61ytk1moi3-IN/image;s=120x89", "description": "\u0d2b\u0d7c\u0d23\u0d3f\u0d1a\u0d4d\u0d1a\u0d7c \u0d15\u0d2f\u0d4d\u0d2f\u0d3f\u0d32\u0d41\u0d23\u0d4d\u0d1f\u0d46\u0d19\u0d4d\u0d15\u0d3f\u0d7d \u0d2a\u0d3f\u0d28\u0d4d\u0d28\u0d46 \u0d15\u0d3e\u0d32\u0d3f \u0d2b\u0d4d\u0d32\u0d3e\u0d31\u0d4d\u0d31\u0d4d \u0d24\u0d28\u0d4d\u0d28\u0d32\u0d4d\u0d32\u0d47 \u0d1a\u0d47\u0d1f\u0d4d\u0d1f\u0d3e \u0d32\u0d3e\u0d2d\u0d02 .  \u0d28\u0d4b\u0d15\u0d4d\u0d15\u0d3e\u0d02 \u0d28\u0d32\u0d4d\u0d32 \u0d2b\u0d4d\u0d32\u0d3e\u0d31\u0d4d\u0d31\u0d41\u0d15\u0d7e Brokees \u0d32\u0d42\u0d1f\u0d46", "location": "Thondayad,Kozhikode,Kerala", "property type": "Apartments", "bathrooms": " 3 Ba ", "bedrooms": "3 Bds ", "furnishing": "Semi-Furnished", "super buildup area": "1980", "carpet area": "1700", "total_sqft": " 1980 ft2"}
{"property_id": "1634595143", "price": "\u20b9 19,000", "image_url": "https://apollo-singapore.akamaized.net:443/v1/files/ujy1mp8rb6nb2-IN/image;s=120x90", "description": "\u0d35\u0d3e\u0d1f\u0d15 \u0d2b\u0d4d\u0d32\u0d3e\u0d31\u0d4d\u0d31\u0d41\u0d02 \u0d24\u0d2a\u0d4d\u0d2a\u0d3f \u0d07\u0d19\u0d4d\u0d19\u0d28\u0d46 \u0d26\u0d3f\u0d35\u0d38\u0d35\u0d41\u0d02 \u0d15\u0d41\u0d1f\u0d41\u0d02\u0d2c\u0d35\u0d41\u0d2e\u0d4a\u0d24\u0d4d\u0d24\u0d4d \u0d05\u0d32\u0d2f\u0d3e\u0d02 \u0d0e\u0d28\u0d4d\u0d28\u0d3e\u0d23\u0d4b \u0d1a\u0d47\u0d1f\u0d4d\u0d1f\u0d3e \u0d35\u0d3f\u0d1a\u0d3e\u0d30\u0d3f\u0d1a\u0d4d\u0d1a\u0d3f\u0d30\u0d3f\u0d15\u0d4d\u0d15\u0d41\u0d28\u0d4d\u0d28\u0d46 ?  \u0d05\u0d2a\u0d15\u0d1f\u0d2e\u0d3e\u0d23\u0d4d .  \u0d15\u0d4a\u0d31\u0d4b\u0d23 \u0d05\u0d24\u0d40\u0d35 \u0d05\u0d2a\u0d15\u0d1f\u0d15\u0d3e\u0d30\u0d3f\u0d2f\u0d41\u0d02 .  Jst ring our nbr , tell us your reqrmnt, waits for the option in your whtsapp. Select the best one , close the deal.  Welcome to Brokees        We are Kerala leading real estate marketing company specialising in the end-to-end solution for property renting,  leasing,  buying and selling. Which present in Calicut Cochin Kannur ,Trivandram, Thrissur and Kottayam. we are your most reliable and trusted real estate partner.                      Your search for a rental flat, Villa or house ends here. We are an expert property finder with serving more than hundred thousand tenants across Kerala.      \u2022) 6 month rental replacement guarantee,  \u2022) Deep cleaned and sanitized units,  \u2022)  Basic connection setup assistance and \u2022) Hassle-free documentation  \u2022) 30% off in Commission charges      These makes us way ahead then our competitors. Just give us 24 working hours to show you the exact property you have been hunting for. \u0d0e\u0d28\u0d4d\u0d24\u0d3f\u0d28\u0d3e \u0d1a\u0d19\u0d4d\u0d19\u0d3e\u0d24\u0d3f \u0d2b\u0d4d\u0d32\u0d3e\u0d31\u0d4d\u0d31\u0d41\u0d02 /\u0d35\u0d40\u0d1f\u0d41\u0d02 \u0d24\u0d2a\u0d4d\u0d2a\u0d3f \u0d35\u0d3f\u0d32\u0d2a\u0d4d\u0d2a\u0d46\u0d1f\u0d4d\u0d1f \u0d38\u0d2e\u0d2f\u0d02 \u0d15\u0d33\u0d2f\u0d41\u0d28\u0d4d\u0d28\u0d46 ?  brokees \u0d7d \u0d35\u0d28\u0d4d\u0d28\u0d3e\u0d7d \u0d0e\u0d32\u0d4d\u0d32\u0d3e\u0d24\u0d4d\u0d24\u0d3f\u0d28\u0d41\u0d02 \u0d09\u0d24\u0d4d\u0d24\u0d30\u0d02 \u0d06\u0d2f\u0d3f\u0d32\u0d4d\u0d32\u0d47 . \u0d28\u0d3f\u0d19\u0d4d\u0d19\u0d33\u0d41\u0d1f\u0d46 \u0d2e\u0d28\u0d38\u0d3f\u0d32\u0d46 \u0d06\u0d35\u0d3f\u0d36\u0d4d\u0d2f\u0d19\u0d4d\u0d19\u0d7e \u0d05\u0d31\u0d3f\u0d2f\u0d3f\u0d15\u0d4d\u0d15\u0d41 ,\u0d1a\u0d47\u0d30\u0d41\u0d28\u0d4d\u0d28 \u0d2b\u0d4d\u0d32\u0d3e\u0d31\u0d4d\u0d31\u0d41\u0d15\u0d7e /\u0d35\u0d40\u0d1f\u0d41\u0d15\u0d7e \u0d1e\u0d19\u0d4d\u0d19\u0d7e \u0d28\u0d7d\u0d15\u0d3e\u0d02  HURRY GET YOUR APPOINTMENT NOW", "location": "Thondayad,Kozhikode,Kerala", "property type": "Apartments", "bathrooms": " 2 Ba ", "bedrooms": "2 Bds ", "furnishing": "Semi-Furnished", "super buildup area": "1430", "carpet area": "1180", "total_sqft": " 1430 ft2"}
{"property_id": "1634354452", "price": "\u20b9 24,000", "image_url": "https://apollo-singapore.akamaized.net:443/v1/files/0osebs5se6df-IN/image;s=120x90", "description": "Looking for a rental House in city ?? Welcome to Brokees        We are Kerala leading real estate marketing company specialising in the end-to-end solution for property renting,  leasing,  buying and selling. Which present in Calicut Cochin Kannur ,Trivandram, Thrissur and Kottayam. we are your most reliable and trusted real estate partner.                      Your search for a rental flat, Villa or house ends here. We are an expert property finder with serving more than hundred thousand tenants across Kerala.      \u2022) 6 month rental replacement guarantee,  \u2022) Deep cleaned and sanitized units,  \u2022)  Basic connection setup assistance and \u2022) Hassle-free documentation  \u2022) 30% off in Commission charges      These makes us way ahead then our competitors. Just give us 24 working hours to show you the exact property you have been hunting for.", "location": "Thondayad,Kozhikode,Kerala", "property type": "Apartments", "bathrooms": " 2 Ba ", "bedrooms": "2 Bds ", "furnishing": "Furnished", "super buildup area": "1350", "carpet area": "1035", "total_sqft": " 1350 ft2"}
{"property_id": "1639841231", "price": "\u20b9 30,000", "image_url": "https://apollo-singapore.akamaized.net:443/v1/files/nv2ylyfvl47k1-IN/image;s=120x160", "description": "2bhk fully furnished flat for rent at Calicut", "location": "Thondayad,Kozhikode,Kerala", "property type": "Apartments", "bathrooms": " 3 Ba ", "bedrooms": "2 Bds ", "furnishing": "Furnished", "super buildup area": "1400", "carpet area": "1350", "total_sqft": " 1400 ft2"}
{"property_id": "1595160286", "price": "\u20b9 21,000", "image_url": "https://apollo-singapore.akamaized.net:443/v1/files/lmqkeqgc29ns2-IN/image;s=120x160", "description": "1bhk fully furnished flat for rent at Calicut", "location": "Thondayad,Kozhikode,Kerala", "property type": "Apartments", "bathrooms": " 2 Ba ", "bedrooms": "1 Bds ", "furnishing": "Furnished", "super buildup area": "700", "carpet area": "700", "total_sqft": " 700 ft2"}
{"property_id": "1726432078", "price": "\u20b9 35,000", "image_url": "https://apollo-singapore.akamaized.net:443/v1/files/vwwjuxcz7fku1-IN/image;s=120x90", "description": "Well water compound wall can use office purpise", "location": "Nadakkavu,Kozhikode,Kerala", "property type": "Houses & Villas", "bathrooms": " 4 Ba ", "bedrooms": "4 Bds ", "furnishing": "Unfurnished", "super buildup area": "2500", "carpet area": "600", "total_sqft": " 2500 ft2"}
{"property_id": "1616528110", "price": "\u20b9 24,500", "image_url": "https://apollo-singapore.akamaized.net:443/v1/files/yjkbhrbaqncc2-IN/image;s=120x159", "description": "Looking for a rental flat in city ? Get all available options in the city ,select the best from it .   Welcome to Brokees         We are Kerala leading real estate marketing company specialising in the end-to-end solution for property renting,  leasing,  buying and selling. Which present in Calicut Cochin Kannur Thrissur and Kottayam. we are your most reliable and trusted real estate partner.                      Your search for a rental flat, Villa or house ends here. We are an expert property finder with serving more than hundred thousand tenants across Kerala.      \u2022) 6 month rental replacement guarantee,  \u2022) Deep cleaned and sanitized units,  \u2022)  Basic connection setup assistance and \u2022) Hassle-free documentation       These makes us way ahead then our competitors. Just give us 24 working hours to show you the exact property you have been hunting for.   HURRY GET YOUR APPOINTMENT NOW", "location": "Thondayad,Kozhikode,Kerala", "property type": "Apartments", "bathrooms": " 2 Ba ", "bedrooms": "2 Bds ", "furnishing": "Furnished", "super buildup area": "1780", "carpet area": "1560", "total_sqft": " 1780 ft2"}
{"property_id": "1616093358", "price": "\u20b9 23,000", "image_url": "https://apollo-singapore.akamaized.net:443/v1/files/3jqza0nm16821-IN/image;s=120x90", "description": "Looking for a rental flat in city ?? Get  all options of rentAl flat in City . Looking for a rental flat in city ?  Welcome to Brokees         We are Kerala leading real estate marketing company specialising in the end-to-end solution for property renting,  leasing,  buying and selling. Which present in Calicut Cochin Kannur Thrissur and Kottayam. we are your most reliable and trusted real estate partner.                      Your search for a rental flat, Villa or house ends here. We are an expert property finder with serving more than hundred thousand tenants across Kerala.      \u2022) 6 month rental replacement guarantee,  \u2022) Deep cleaned and sanitized units,  \u2022)  Basic connection setup assistance and \u2022) Hassle-free documentation       These makes us way ahead then our competitors. Just give us 24 working hours to show you the exact property you have been hunting for.   HURRY GET YOUR APPOINTMENT NOW", "location": "Thondayad,Kozhikode,Kerala", "property type": "Apartments", "bathrooms": " 2 Ba ", "bedrooms": "2 Bds ", "furnishing": "Furnished", "super buildup area": "1370", "carpet area": "1020", "total_sqft": " 1370 ft2"}
{"property_id": "1613373744", "price": "\u20b9 23,000", "image_url": "https://apollo-singapore.akamaized.net:443/v1/files/hdybj7yg76om1-IN/image;s=120x89", "description": "Looking for a rental option in Kochi?   Your wish granted .", "location": "Thondayad,Kozhikode,Kerala", "property type": "Apartments", "bathrooms": " 2 Ba ", "bedrooms": "2 Bds ", "furnishing": "Furnished", "super buildup area": "1340", "carpet area": "1020", "total_sqft": " 1340 ft2"}
{"property_id": "1612856306", "price": "\u20b9 25,000", "image_url": "https://apollo-singapore.akamaized.net:443/v1/files/92fam4272oqj3-IN/image;s=120x90", "description": "Welcome to Brokees         We are Kerala leading real estate marketing company specialising in the end-to-end solution for property renting,  leasing,  buying and selling. Which present in Calicut Cochin Kannur Thrissur and Kottayam. we are your most reliable and trusted real estate partner.                      Your search for a rental flat, Villa or house ends here. We are an expert property finder with serving more than hundred thousand tenants across Kerala.      \u2022) 6 month rental replacement guarantee,  \u2022) Deep cleaned and sanitized units,  \u2022)  Basic connection setup assistance and \u2022) Hassle-free documentation       These makes us way ahead then our competitors. Just give us 24 working hours to show you the exact property you have been hunting for.   HURRY GET YOUR APPOINTMENT NOW", "location": "Thondayad,Kozhikode,Kerala", "property type": "Apartments", "bathrooms": " 2 Ba ", "bedrooms": "2 Bds ", "furnishing": "Furnished", "super buildup area": "1340", "carpet area": "1030", "total_sqft": " 1340 ft2"}
{"property_id": "1612855381", "price": "\u20b9 22,000", "image_url": "https://apollo-singapore.akamaized.net:443/v1/files/i0t4d36ydqzv1-IN/image;s=120x89", "description": "Welcome to Brokees         We are Kerala leading real estate marketing company specialising in the end-to-end solution for property renting,  leasing,  buying and selling. Which present in Calicut Cochin Kannur Thrissur and Kottayam. we are your most reliable and trusted real estate partner.                      Your search for a rental flat, Villa or house ends here. We are an expert property finder with serving more than hundred thousand tenants across Kerala.      \u2022) 6 month rental replacement guarantee,  \u2022) Deep cleaned and sanitized units,  \u2022)  Basic connection setup assistance and \u2022) Hassle-free documentation       These makes us way ahead then our competitors. Just give us 24 working hours to show you the exact property you have been hunting for.   HURRY GET YOUR APPOINTMENT NOW", "location": "Thondayad,Kozhikode,Kerala", "property type": "Apartments", "bathrooms": " 2 Ba ", "bedrooms": "2 Bds ", "furnishing": "Furnished", "super buildup area": "1320", "carpet area": "1102", "total_sqft": " 1320 ft2"}
{"property_id": "1665233041", "price": "\u20b9 22,000", "image_url": "https://apollo-singapore.akamaized.net:443/v1/files/yzqool9bhjew2-IN/image;s=120x89", "description": "\u0d05\u0d24\u0d46 \u0d0e\u0d2a\u0d4d\u0d2a\u0d4b\u0d34\u0d41\u0d02 \u0d35\u0d3e\u0d1f\u0d15 \u0d35\u0d40\u0d1f\u0d4d \u0d28\u0d4b\u0d15\u0d4d\u0d15\u0d41\u0d2e\u0d4d\u0d2a\u0d4b\u0d7e \u0d28\u0d3e\u0d02 \u0d05\u0d2d\u0d3f\u0d2e\u0d41\u0d16\u0d40\u0d15\u0d30\u0d3f\u0d15\u0d4d\u0d15\u0d41\u0d28\u0d4d\u0d28 \u0d2a\u0d4d\u0d30\u0d27\u0d3e\u0d28 \u0d2a\u0d4d\u0d30\u0d36\u0d4d\u0d28\u0d02 \u0d35\u0d43\u0d24\u0d4d\u0d24\u0d3f \u0d07\u0d32\u0d4d\u0d32\u0d3e\u0d2f\u0d4d\u0d2e \u0d2d\u0d02\u0d17\u0d3f \u0d15\u0d41\u0d31\u0d35\u0d4d \u0d0e\u0d28\u0d4d\u0d28\u0d3f\u0d35 \u0d24\u0d28\u0d4d\u0d28\u0d46\u0d2f\u0d3e\u0d23\u0d4d \u0d07\u0d35\u0d2f\u0d46\u0d32\u0d4d\u0d32\u0d3e\u0d02 \u0d12\u0d30\u0d41\u0d2e\u0d3f\u0d15\u0d4d\u0d15\u0d41\u0d28\u0d4d\u0d28 \u0d15\u0d4b\u0d34\u0d3f\u0d15\u0d4d\u0d15\u0d4b\u0d1f\u0d4d \u0d28\u0d17\u0d30\u0d24\u0d4d\u0d24\u0d3f\u0d7d \u0d28\u0d3f\u0d19\u0d4d\u0d19\u0d7e\u0d15\u0d4d\u0d15\u0d4d \u0d32\u0d2d\u0d3f\u0d15\u0d4d\u0d15\u0d41\u0d28\u0d4d\u0d28 \u0d2e\u0d3f\u0d15\u0d1a\u0d4d\u0d1a \u0d13\u0d2a\u0d4d\u0d37\u0d7b Brokees \u0d28\u0d7d\u0d15\u0d41\u0d28\u0d4d\u0d28\u0d41.  Get your appointment now", "location": "Thondayad,Kozhikode,Kerala", "property type": "Houses & Villas", "bathrooms": " 3 Ba ", "bedrooms": "4 Bds ", "furnishing": "Semi-Furnished", "super buildup area": "2200", "carpet area": "1930", "total_sqft": " 2200 ft2"}
{"property_id": "1634963433", "price": "\u20b9 20,000", "image_url": "https://apollo-singapore.akamaized.net:443/v1/files/899ffxt5e9yt1-IN/image;s=120x90", "description": "\u0d15\u0d4b\u0d34\u0d3f\u0d15\u0d4d\u0d15\u0d4b\u0d1f\u0d46 \u0d28\u0d32\u0d4d\u0d32 \u0d28\u0d32\u0d4d\u0d32 \u0d05\u0d1f\u0d3f\u0d2a\u0d4a\u0d33\u0d3f \u0d35\u0d40\u0d1f\u0d41\u0d15\u0d7e Brokees \u0d7d \u0d09\u0d33\u0d4d\u0d33\u0d2a\u0d4d\u0d2a\u0d4b\u0d7e \u0d2a\u0d3f\u0d28\u0d4d\u0d28\u0d46\u0d28\u0d4d\u0d24\u0d3f\u0d28\u0d3e  \u0d1a\u0d47\u0d1f\u0d4d\u0d1f\u0d3e \u0d07\u0d24\u0d3f\u0d19\u0d4d\u0d19\u0d28\u0d46 \u0d24\u0d2a\u0d4d\u0d2a\u0d3f \u0d05\u0d32\u0d1e\u0d4d\u0d1e\u0d41 \u0d15\u0d4a\u0d31\u0d4b\u0d23 \u0d35\u0d30\u0d41\u0d24\u0d4d\u0d24\u0d41\u0d28\u0d4d\u0d28\u0d47 ?   \u0d05\u0d2a\u0d4d\u0d2a\u0d4b \u0d0e\u0d32\u0d4d\u0d32\u0d3e\u0d02 \u0d2a\u0d31\u0d1e\u0d4d\u0d1e \u0d2a\u0d4b\u0d32\u0d46 Brokees \u0d32\u0d47\u0d15\u0d4d\u0d15\u0d4d \u0d35\u0d28\u0d4d\u0d28\u0d4b\u0d33\u0d40 \u0d1f\u0d4d\u0d1f\u0d4b .", "location": "Thondayad,Kozhikode,Kerala", "property type": "Houses & Villas", "bathrooms": " 3 Ba ", "bedrooms": "4 Bds ", "furnishing": "Semi-Furnished", "super buildup area": "2350", "carpet area": "2135", "total_sqft": " 2350 ft2"}
{"property_id": "1634961797", "price": "\u20b9 20,500", "image_url": "https://apollo-singapore.akamaized.net:443/v1/files/vko2j8k7o8yi2-IN/image;s=120x86", "description": "\u0d15\u0d4b\u0d34\u0d3f\u0d15\u0d4d\u0d15\u0d4b\u0d1f\u0d4d \u0d12\u0d30\u0d41 \u0d24\u0d3e\u0d2e\u0d38 \u0d38\u0d4d\u0d35\u0d15\u0d3e\u0d30\u0d4d\u0d2f\u0d02 \u0d06\u0d23\u0d4d \u0d28\u0d3f\u0d19\u0d4d\u0d19\u0d7e \u0d28\u0d4b\u0d15\u0d4d\u0d15\u0d41\u0d28\u0d4d\u0d28\u0d24\u0d46\u0d19\u0d4d\u0d15\u0d3f\u0d7d Brokees \u0d7d \u0d05\u0d24\u0d3f\u0d28\u0d41\u0d33\u0d4d\u0d33 \u0d2a\u0d30\u0d3f\u0d39\u0d3e\u0d30\u0d02 \u0d09\u0d23\u0d4d\u0d1f\u0d4d .  \u0d2b\u0d3e\u0d2e\u0d3f\u0d32\u0d3f \u0d06\u0d2f\u0d41\u0d02 \u0d2c\u0d3e\u0d1a\u0d4d\u0d1a\u0d3f\u0d32\u0d7c \u0d06\u0d2f\u0d41\u0d02 \u0d24\u0d3e\u0d2e\u0d38\u0d3f\u0d15\u0d4d\u0d15\u0d41\u0d35\u0d3e\u0d7b \u0d2a\u0d31\u0d4d\u0d31\u0d3f\u0d2f \u0d07\u0d1f\u0d02 \u0d1e\u0d19\u0d4d\u0d19\u0d7e \u0d28\u0d7d\u0d15\u0d3e\u0d02 .   Get your appointment Now", "location": "Thondayad,Kozhikode,Kerala", "property type": "Apartments", "bathrooms": " 1 Ba ", "bedrooms": "1 Bds ", "furnishing": "Furnished", "super buildup area": "1000", "carpet area": "760", "total_sqft": " 1000 ft2"}
{"property_id": "1634961207", "price": "\u20b9 24,000", "image_url": "https://apollo-singapore.akamaized.net:443/v1/files/m7tf2oxcrf2h3-IN/image;s=120x120", "description": "\u0d38\u0d41\u0d28\u0d4d\u0d26\u0d30\u0d3f\u0d2f\u0d3e\u0d2f \u0d12\u0d30\u0d41 \u0d2b\u0d4d\u0d32\u0d3e\u0d31\u0d4d\u0d31\u0d4d \u0d05\u0d19\u0d4d\u0d19\u0d1f\u0d4d \u0d24\u0d28\u0d4d\u0d28\u0d47\u0d15\u0d4d\u0d15\u0d3e\u0d02 ,\u0d35\u0d28\u0d4d\u0d28\u0d4b\u0d33\u0d42 \u0d28\u0d4b\u0d15\u0d4d\u0d15\u0d23\u0d4d\u0d1f \u0d1a\u0d47\u0d1f\u0d4d\u0d1f\u0d3e ,,\u0d0e\u0d24\u0d41 \u0d35\u0d40\u0d1f\u0d41\u0d02 \u0d2b\u0d4d\u0d32\u0d3e\u0d31\u0d4d\u0d31\u0d41\u0d02 \u0d2d\u0d02\u0d17\u0d3f \u0d2f\u0d41\u0d33\u0d4d\u0d33\u0d24\u0d3e\u0d35\u0d41\u0d28\u0d4d\u0d28\u0d24\u0d4d \u0d05\u0d24\u0d3f\u0d28\u0d4d\u0d31\u0d46 \u0d07\u0d28\u0d4d\u0d31\u0d40\u0d30\u0d3f\u0d2f\u0d7c \u0d15\u0d4a\u0d23\u0d4d\u0d1f\u0d41\u0d2e\u0d3e\u0d24\u0d4d\u0d30\u0d2e\u0d32\u0d4d\u0d32 ,\u0d05\u0d35\u0d3f\u0d1f\u0d46\u0d1f\u0d41\u0d33\u0d4d\u0d33 \u0d15\u0d41\u0d1f\u0d41\u0d02\u0d2c\u0d24\u0d4d\u0d24\u0d3f\u0d28\u0d4d\u0d31\u0d46 \u0d38\u0d28\u0d4d\u0d24\u0d4b\u0d37\u0d02 \u0d15\u0d4a\u0d23\u0d4d\u0d1f\u0d41\u0d02 \u0d06\u0d23\u0d4d .  \u0d28\u0d32\u0d4d\u0d32\u0d4a\u0d30\u0d41 \u0d1c\u0d40\u0d35\u0d3f\u0d24\u0d3e\u0d28\u0d4d\u0d24\u0d30\u0d40\u0d15\u0d4d\u0d37\u0d02 \u0d28\u0d3f\u0d19\u0d4d\u0d19\u0d7e\u0d15\u0d4d\u0d15\u0d4d Brokees \u0d32\u0d42\u0d1f\u0d46 \u0d38\u0d4d\u0d35\u0d28\u0d4d\u0d24\u0d2e\u0d3e\u0d15\u0d4d\u0d15\u0d3e\u0d02 . Get your appointment Now", "location": "Thondayad,Kozhikode,Kerala", "property type": "Apartments", "bathrooms": " 2 Ba ", "bedrooms": "2 Bds ", "furnishing": "Furnished", "super buildup area": "1325", "carpet area": "1034", "total_sqft": " 1325 ft2"}
{"property_id": "1634928919", "price": "\u20b9 20,000", "image_url": "https://apollo-singapore.akamaized.net:443/v1/files/hl3pj0o2ssii1-IN/image;s=120x157", "description": "Your search for a rental Home ends here.  Welcome to Brokees. \u0d08 \u0d15\u0d4a\u0d31\u0d4b\u0d23 \u0d38\u0d2e\u0d2f\u0d24\u0d4d\u0d24\u0d41 \u0d35\u0d3e\u0d1f\u0d15\u0d2f\u0d4d\u0d15\u0d4d\u0d15\u0d4d \u0d2b\u0d4d\u0d32\u0d3e\u0d31\u0d4d\u0d31\u0d4d /\u0d35\u0d40\u0d1f\u0d4d \u0d24\u0d2a\u0d4d\u0d2a\u0d3f \u0d35\u0d46\u0d31\u0d41\u0d24\u0d46 \u0d05\u0d32\u0d1e\u0d4d\u0d1e\u0d41 \u0d28\u0d1f\u0d28\u0d4d\u0d28\u0d41 \u0d15\u0d41\u0d1f\u0d41\u0d02\u0d2c\u0d24\u0d4d\u0d24\u0d3f\u0d28\u0d4d \u0d28\u0d3e\u0d25\u0d28\u0d3f\u0d32\u0d4d\u0d32\u0d3e\u0d24\u0d3e\u0d15\u0d4d\u0d15\u0d23\u0d4b ?  \u0d35\u0d47\u0d17\u0d02 Brokees \u0d32\u0d47\u0d15\u0d4d\u0d15\u0d4d \u0d35\u0d28\u0d4d\u0d28\u0d4b\u0d33\u0d42 .  Get your appointment now", "location": "Thondayad,Kozhikode,Kerala", "property type": "Apartments", "bathrooms": " 4 Ba ", "bedrooms": "4 Bds ", "furnishing": "Semi-Furnished", "super buildup area": "2420", "carpet area": "2110", "total_sqft": " 2420 ft2"}
{"property_id": "1671368892", "price": "\u20b9 18,000", "image_url": "https://apollo-singapore.akamaized.net:443/v1/files/o10lspvwuy8j-IN/image;s=120x67", "description": "\u0d1a\u0d41\u0d2e\u0d4d\u0d2e\u0d3e \u0d0e\u0d28\u0d4d\u0d24\u0d3f\u0d28\u0d3e \u0d1a\u0d47\u0d1f\u0d4d\u0d1f\u0d3e \u0d2b\u0d7c\u0d23\u0d3f\u0d1a\u0d4d\u0d1a\u0d7c \u0d15\u0d2f\u0d4d\u0d2f\u0d3f\u0d32\u0d41\u0d23\u0d4d\u0d1f\u0d46\u0d19\u0d4d\u0d15\u0d3f\u0d7d \u0d07\u0d19\u0d4d\u0d19\u0d28\u0d46 \u0d05\u0d27\u0d3f\u0d15 \u0d35\u0d3e\u0d1f\u0d15 \u0d15\u0d4a\u0d1f\u0d41\u0d15\u0d4d\u0d15\u0d3e\u0d7b \u0d28\u0d3f\u0d7d\u0d15\u0d4d\u0d15\u0d41\u0d28\u0d4d\u0d28\u0d46? \u0d38\u0d46\u0d2e\u0d3f \u0d2b\u0d7c\u0d23\u0d3f\u0d1a\u0d4d\u0d1a\u0d7c \u0d09\u0d33\u0d4d\u0d33 \u0d2b\u0d4d\u0d32\u0d3e\u0d31\u0d4d\u0d31\u0d4d \u0d0e\u0d1f\u0d41\u0d24\u0d4d\u0d24\u0d3f\u0d1f\u0d4d\u0d1f\u0d4d \u0d2b\u0d7c\u0d23\u0d3f\u0d1a\u0d4d\u0d1a\u0d7c \u0d28\u0d3f\u0d19\u0d4d\u0d19\u0d7e \u0d1a\u0d46\u0d2f\u0d4d\u0d2f\u0d41\u0d15\u0d2f\u0d3e\u0d23\u0d46\u0d19\u0d4d\u0d15\u0d3f\u0d7d \u0d28\u0d3f\u0d19\u0d4d\u0d19\u0d7e\u0d15\u0d4d\u0d15\u0d4d \u0d35\u0d32\u0d3f\u0d2f \u0d32\u0d3e\u0d2d\u0d02 \u0d24\u0d28\u0d4d\u0d28\u0d46 \u0d2e\u0d3e\u0d38\u0d4d \u0d35\u0d3e\u0d1f\u0d15\u0d2f\u0d3f\u0d7d \u0d09\u0d23\u0d4d\u0d1f\u0d3e\u0d35\u0d41\u0d02 \u0d05\u0d24\u0d4d \u0d35\u0d7c\u0d37\u0d3e\u0d35\u0d7c\u0d37\u0d02 \u0d28\u0d4b\u0d15\u0d4d\u0d15\u0d41\u0d2e\u0d4d\u0d2a\u0d4b\u0d7e \u0d35\u0d32\u0d3f\u0d2f\u0d4a\u0d30\u0d41 \u0d32\u0d3e\u0d2d\u0d02 \u0d28\u0d3f\u0d19\u0d4d\u0d19\u0d7e\u0d15\u0d4d\u0d15\u0d4d \u0d09\u0d23\u0d4d\u0d1f\u0d3e\u0d35\u0d41\u0d02 \u0d0e\u0d28\u0d4d\u0d28\u0d24\u0d3f\u0d7d \u0d12\u0d30\u0d41 \u0d38\u0d02\u0d36\u0d2f\u0d35\u0d41\u0d2e\u0d3f\u0d32\u0d4d\u0d32", "location": "Thondayad,Kozhikode,Kerala", "property type": "Apartments", "bathrooms": " 2 Ba ", "bedrooms": "2 Bds ", "furnishing": "Semi-Furnished", "super buildup area": "1380", "carpet area": "1120", "total_sqft": " 1380 ft2"}
{"property_id": "1671254599", "price": "\u20b9 21,000", "image_url": "https://apollo-singapore.akamaized.net:443/v1/files/s7bxurn369bk-IN/image;s=120x120", "description": "Get your appoitment now", "location": "Thondayad,Kozhikode,Kerala", "property type": "Houses & Villas", "bathrooms": " 3 Ba ", "bedrooms": "3 Bds ", "furnishing": "Semi-Furnished", "super buildup area": "1560", "carpet area": "1320", "total_sqft": " 1560 ft2"}
{"property_id": "1667217713", "price": "\u20b9 19,000", "image_url": "https://apollo-singapore.akamaized.net:443/v1/files/ws0w88irywgf1-IN/image;s=120x90", "description": "\u0d15\u0d47\u0d30\u0d33\u0d24\u0d4d\u0d24\u0d3f\u0d32\u0d46 \u0d0f\u0d24\u0d4d \u0d1c\u0d3f\u0d32\u0d4d\u0d32\u0d15\u0d7e \u0d28\u0d4b\u0d15\u0d4d\u0d15\u0d41\u0d15\u0d2f\u0d3e\u0d23\u0d46\u0d19\u0d4d\u0d15\u0d3f\u0d7d \u0d09\u0d02 \u0d15\u0d4b\u0d34\u0d3f\u0d15\u0d4d\u0d15\u0d4b\u0d1f\u0d4d \u0d38\u0d3f\u0d31\u0d4d\u0d31\u0d3f \u0d05\u0d24\u0d3f\u0d7d \u0d15\u0d42\u0d1f\u0d41\u0d24\u0d7d \u0d35\u0d3e\u0d1f\u0d15 \u0d1a\u0d4b\u0d26\u0d3f\u0d15\u0d4d\u0d15\u0d41\u0d28\u0d4d\u0d28 \u0d12\u0d30\u0d41 \u0d38\u0d3f\u0d31\u0d4d\u0d31\u0d3f\u0d2f\u0d3e\u0d23\u0d4d.   \u0d06\u0d2f\u0d24\u0d3f\u0d28\u0d3e\u0d7d \u0d24\u0d28\u0d4d\u0d28\u0d46 \u0d15\u0d4b\u0d34\u0d3f\u0d15\u0d4d\u0d15\u0d4b\u0d1f\u0d4d \u0d12\u0d30\u0d41 \u0d2b\u0d7c\u0d23\u0d3f\u0d1a\u0d4d\u0d1a\u0d7c \u0d09\u0d33\u0d4d\u0d33 \u0d2b\u0d4d\u0d32\u0d3e\u0d31\u0d4d\u0d31\u0d4d \u0d0e\u0d1f\u0d41\u0d15\u0d4d\u0d15\u0d41\u0d28\u0d4d\u0d28\u0d24\u0d3f\u0d28\u0d47\u0d15\u0d4d\u0d15\u0d3e\u0d7e \u0d32\u0d3e\u0d2d\u0d15\u0d30\u0d02 \u0d28\u0d3f\u0d19\u0d4d\u0d19\u0d7e\u0d15\u0d4d\u0d15\u0d4d \u0d2b\u0d7c\u0d23\u0d3f\u0d1a\u0d4d\u0d1a\u0d7c \u0d07\u0d32\u0d4d\u0d32\u0d3e\u0d24\u0d4d\u0d24 \u0d12\u0d30\u0d41 \u0d2b\u0d4d\u0d32\u0d3e\u0d31\u0d4d\u0d31\u0d4d \u0d35\u0d3e\u0d1f\u0d15\u0d2f\u0d4d\u0d15\u0d4d\u0d15\u0d4d \u0d0e\u0d1f\u0d41\u0d15\u0d4d\u0d15\u0d41\u0d28\u0d4d\u0d28\u0d24\u0d4d \u0d24\u0d28\u0d4d\u0d28\u0d46\u0d2f\u0d3e\u0d23\u0d4d.   \u0d2b\u0d7c\u0d23\u0d3f\u0d1a\u0d4d\u0d1a\u0d7c \u0d07\u0d32\u0d4d\u0d32\u0d3e\u0d24\u0d4d\u0d24 \u0d2e\u0d3f\u0d15\u0d1a\u0d4d\u0d1a \u0d2b\u0d4d\u0d32\u0d3e\u0d31\u0d4d\u0d31\u0d41\u0d15\u0d33\u0d41\u0d1f\u0d46 \u0d12\u0d30\u0d41 \u0d36\u0d4d\u0d30\u0d47\u0d23\u0d3f \u0d24\u0d28\u0d4d\u0d28\u0d46 \u0d28\u0d3f\u0d19\u0d4d\u0d19\u0d7e\u0d15\u0d4d\u0d15\u0d4d \u0d1e\u0d19\u0d4d\u0d19\u0d7e \u0d12\u0d30\u0d41\u0d15\u0d4d\u0d15\u0d3f\u0d2f\u0d3f\u0d30\u0d3f\u0d15\u0d4d\u0d15\u0d41\u0d28\u0d4d\u0d28\u0d41 \u0d28\u0d3f\u0d19\u0d4d\u0d19\u0d33\u0d41\u0d1f\u0d46 \u0d2c\u0d1c\u0d31\u0d4d\u0d31\u0d4d \u0d10\u0d21\u0d3f\u0d2f \u0d0e\u0d28\u0d4d\u0d28\u0d3f\u0d35 \u0d2a\u0d31\u0d2f\u0d41\u0d15\u0d2f\u0d3e\u0d23\u0d46\u0d19\u0d4d\u0d15\u0d3f\u0d7d \u0d05\u0d24\u0d3f\u0d28\u0d4a\u0d24\u0d4d\u0d24 \u0d2a\u0d4d\u0d30\u0d4b\u0d1c\u0d15\u0d4d\u0d1f\u0d41\u0d15\u0d7e \u0d28\u0d3f\u0d19\u0d4d\u0d19\u0d7e\u0d15\u0d4d\u0d15\u0d4d \u0d32\u0d2d\u0d3f\u0d15\u0d4d\u0d15\u0d41\u0d28\u0d4d\u0d28\u0d24\u0d3e\u0d23\u0d4d.", "location": "Thondayad,Kozhikode,Kerala", "property type": "Apartments", "bathrooms": " 2 Ba ", "bedrooms": "2 Bds ", "furnishing": "Semi-Furnished", "super buildup area": "1430", "carpet area": "1150", "total_sqft": " 1430 ft2"}
{"property_id": "1728807014", "price": "\u20b9 20,000", "image_url": "https://apollo-singapore.akamaized.net:443/v1/files/nud177b9e3bz-IN/image;s=120x87", "description": "2 bhik flat", "location": "Pottakkad,Kozhikode,Kerala", "property type": "Apartments", "bathrooms": " 2 Ba ", "bedrooms": "2 Bds ", "furnishing": "Semi-Furnished", "super buildup area": "949", "carpet area": "900", "total_sqft": " 949 ft2"}
{"property_id": "1728806915", "price": "\u20b9 15,000", "image_url": "https://apollo-singapore.akamaized.net:443/v1/files/5vqz0s2d2h1b1-IN/image;s=120x54", "description": "\u0d1a\u0d47\u0d35\u0d3e\u0d2f\u0d42\u0d7c \u0d1a\u0d47\u0d30\u0d2e\u0d4d\u0d2a\u0d32\u0d02 \u0d31\u0d4b\u0d21\u0d3f\u0d7d \u0d28\u0d3f\u0d28\u0d4d\u0d28\u0d4d  300\u0d2e\u0d40\u0d31\u0d4d\u0d31\u0d7c \u0d26\u0d42\u0d30\u0d02", "location": "Chevayoor,Kozhikode,Kerala", "property type": "Houses & Villas", "bathrooms": " 2 Ba ", "bedrooms": "3 Bds ", "furnishing": "Unfurnished", "super buildup area": "1000", "carpet area": "900", "total_sqft": " 1000 ft2"}
{"property_id": "1639833782", "price": "\u20b9 25,000", "image_url": "https://apollo-singapore.akamaized.net:443/v1/files/3gpakjub4baj2-IN/image;s=120x90", "description": "Flat for rent at Landmark, World 2bhk full furnished flat Thondayad. 1400 Sq ft with Luxury    amenities for the comfort residents .It is close to the Nesto supermarket,mall, Education institutions and Hospitals.  Contact.", "location": "Thondayad,Kozhikode,Kerala", "property type": "Apartments", "bathrooms": " 3 Ba ", "bedrooms": "2 Bds ", "furnishing": "Furnished", "super buildup area": "1402", "carpet area": "1320", "total_sqft": " 1402 ft2"}
{"property_id": "1726629358", "price": "\u20b9 20,000", "image_url": "https://apollo-singapore.akamaized.net:443/v1/files/tegzp7lnuq2z-IN/image;s=120x90", "description": "Near MIMS hospital  Upcoming Lulu Mall  2 Bedroom +2 Bathroom+ Living+ Dining+ Workers area+ Balocny  1 Car Park  Furnished  2 Air conditoner  1 Fridge  1 Stove  Sofa set  2 cot + Mattress  1st floor  Close to Railway station Bus stand  Looking for 1 year contract.", "location": "Chalapuram,Kozhikode,Kerala", "property type": "Houses & Villas", "bathrooms": " 2 Ba ", "bedrooms": "2 Bds ", "furnishing": "Furnished", "super buildup area": "1100", "carpet area": "1100", "total_sqft": " 1100 ft2"}
{"property_id": "1675930329", "price": "\u20b9 25,000", "image_url": "https://apollo-singapore.akamaized.net:443/v1/files/etxjmkrguyis3-IN/image;s=120x160", "description": "2bhk Semi furnished flat for rent at Palazhi Kozhikode", "location": "Thondayad,Kozhikode,Kerala", "property type": "Apartments", "bathrooms": " 2 Ba ", "bedrooms": "2 Bds ", "furnishing": "Furnished", "super buildup area": "1515", "carpet area": "1500", "total_sqft": " 1515 ft2"}
